.gitignore
LICENSE
README.md
setup.py
py_buildsystem/__init__.py
py_buildsystem/__main__.py
py_buildsystem/common.py
py_buildsystem.egg-info/PKG-INFO
py_buildsystem.egg-info/SOURCES.txt
py_buildsystem.egg-info/dependency_links.txt
py_buildsystem.egg-info/not-zip-safe
py_buildsystem.egg-info/requires.txt
py_buildsystem.egg-info/top_level.txt
py_buildsystem/ConfigReader/ConfigReader.py
py_buildsystem/ConfigReader/__init__.py
py_buildsystem/FilesFinder/FilesFinder.py
py_buildsystem/FilesFinder/__init__.py
py_buildsystem/Project/Project.py
py_buildsystem/Project/__init__.py
py_buildsystem/Step/Step.py
py_buildsystem/Step/StepCommand.py
py_buildsystem/Step/StepCompile.py
py_buildsystem/Step/StepFactory.py
py_buildsystem/Step/StepGit.py
py_buildsystem/Step/StepLink.py
py_buildsystem/Step/__init__.py
py_buildsystem/Toolchain/Toolchain.py
py_buildsystem/Toolchain/__init__.py
py_buildsystem/Toolchain/Compiler/Compiler.py
py_buildsystem/Toolchain/Compiler/__init__.py
py_buildsystem/Toolchain/Linker/Linker.py
py_buildsystem/Toolchain/Linker/__init__.py
py_buildsystem/Toolchain/ToolchainsConfigs/G++.yaml
py_buildsystem/Toolchain/ToolchainsConfigs/G++_ARM.yaml
py_buildsystem/Toolchain/ToolchainsConfigs/GCC.yaml
py_buildsystem/Toolchain/ToolchainsConfigs/GCC_ARM.yaml
resources/UML/py_buildsystem.uxf
tests/__init__.py
tests/Compiler/__init__.py
tests/Compiler/test_Compiler.py
tests/ConfigReader/__init__.py
tests/ConfigReader/test_ConfigReader.py
tests/FilesFinder/__init__.py
tests/FilesFinder/test_FilesFinder.py
tests/Linker/__init__.py
tests/Linker/test_Linker.py
tests/ProjectConfig/__init__.py
tests/ProjectConfig/test_Project.py