Metadata-Version: 2.1
Name: py-buildsystem
Version: 0.6.0
Summary: python based build system.
Home-page: https://github.com/ProrokWielki/py_buildsystem
Author: Pawel Warzecha
Author-email: pawel.warzecha@yahoo.com
License: MIT
Platform: UNKNOWN
